{
  "type": "feat",
  "name": "Eager Hunter",
  "folder": "KzRoYoxNDV1VRnxT",
  "img": "icons/sundries/books/book-red-exclamation.webp",
  "system": {
    "level": {
      "value": 10
    },
    "category": "class",
    "traits": {
      "value": [
        "slayer"
      ],
      "otherTags": [],
      "rarity": "common"
    },
    "publication": {
      "license": "ORC",
      "remaster": true,
      "title": "Pathfinder Risks & Rewards Playtest",
      "authors": ""
    },
    "description": {
      "value": "<p>You are so eager to reach your prey that every opening propels you forward. When you go @UUID[Compendium.pf2e-playtest-data.rr-playtest-actions.Item.O0SU1cAh8ijq7Z4J]{On the Hunt}, you can Step towards the nearest enemy as a free action.</p>",
      "gm": ""
    },
    "rules": [
      {
        "key": "ItemAlteration",
        "mode": "add",
        "property": "description",
        "predicate": [
          "item:slug:on-the-hunt"
        ],
        "value": [
          {
            "text": "{item|description}"
          }
        ],
        "itemType": "action"
      }
    ],
    "slug": "eager-hunter",
    "_migration": {
      "version": 0.954,
      "previous": {
        "schema": null,
        "foundry": "13.351",
        "system": "7.9.1"
      }
    },
    "onlyLevel1": false,
    "maxTakable": 1,
    "actionType": {
      "value": "passive"
    },
    "actions": {
      "value": null
    },
    "prerequisites": {
      "value": []
    },
    "subfeatures": {
      "proficiencies": {},
      "senses": {},
      "suppressedFeatures": []
    },
    "location": null
  },
  "_id": "jLrLqp7L8N7sGfbd",
  "effects": [],
  "sort": 0,
  "ownership": {
    "default": 0,
    "yECpvB6rPSLHk9Lh": 3
  },
  "flags": {},
  "_stats": {
    "compendiumSource": null,
    "duplicateSource": null,
    "exportSource": null,
    "coreVersion": "13.351",
    "systemId": "pf2e",
    "systemVersion": "7.9.1"
  },
  "_key": "!items!jLrLqp7L8N7sGfbd"
}
